{"title":"Monopoly, But COMMUNIST? No Rolls Barred, a YouTube Channel about board games,...","link":"https://kottke.org/24/09/0045301-monopoly-but-communist-no","date":1726764128000,"content":"\n        <a href=\"https://www.youtube.com/watch?v=jkN6xxyEgZc\">Monopoly, But COMMUNIST?</a> No Rolls Barred, a YouTube Channel about board games, <a href=\"https://www.youtube.com/playlist?list=PLQBGXhGots81MO5NLArB4xelKqRhREzoZ\">has a series of videos featuring Monopoly but with different rules</a>.\n\n        \n\n        \n\n         <p>💬 <a href=\"https://kottke.org/24/09/0045301-monopoly-but-communist-no\">Join the discussion on kottke.org</a> →</p>\n\n    ","author":"Jason Kottke","siteTitle":"Kottke","siteHash":"89a883271b4598f9b33ebe87be70d38557bcd266e68aee521a8f93622e0ab723","entryHash":"13f696ce62b05cf0db77ce99f16a7c27ebd4686cb3a7e6b2940fd2a0a076b48a","category":"Sites"}