{"title":"USPS to Release Ansel Adams Stamps","link":"https://kottke.org/24/02/usps-to-release-ansel-adams-stamps","date":1709138937000,"content":"\n        <p><img src=\"/plus/misc/images/usps-ansel-stamps.jpg\" width=\"1208\" height=\"964\" alt=\"a sheet of stamps from the US Postal Service featuring Ansel Adams photographs\" /></p>\n\n<p>The US Postal Service is set to release <a href=\"https://www.stampinformation.com/2024/stamps/ansel-adams\">a sheet of 16 stamps featuring the legendary photography of Ansel Adams</a>.</p>\n\n<blockquote><p>Ansel Adams made a career of crafting photographs in exquisitely sharp focus and nearly infinite tonality and detail. His ability to consistently visualize a subject — not how it looked in reality but how it felt to him emotionally — led to some of the most famous images of America’s natural treasures including Half Dome in California’s Yosemite Valley, the Grand Tetons in Wyoming, and Denali in Alaska, the highest peak in the United States.</p></blockquote>\n\n<p>No pre-order links yet, but the stamps will be available on <a href=\"https://about.usps.com/newsroom/national-releases/2024/0223-usps-reveals-more-information-on-stamps-for-2024.htm\">May 15</a>. (via <a href=\"https://www.threads.net/@anseladams/post/C30c7kpp8Lj\">@anseladams</a>)</p>\n\n<p>P.S. I was just poking around the official Ansel Adams site and ran across <a href=\"https://shop.anseladams.com/collections/original-photographs-by-ansel-adams/products/woman-behind-screen-door-independence\">this photo I’d never seen before of a woman behind a screen door</a>. Really wonderful.</p>\n\n        \n\n <p><strong>Tags:</strong> <a href=\"https://kottke.org/tag/Ansel%20Adams\">Ansel Adams</a> · <a href=\"https://kottke.org/tag/design\">design</a> · <a href=\"https://kottke.org/tag/photography\">photography</a> · <a href=\"https://kottke.org/tag/stamps\">stamps</a> · <a href=\"https://kottke.org/tag/USPS\">USPS</a></p>\n\n <p>💬 <a href=\"https://kottke.org/24/02/usps-to-release-ansel-adams-stamps\">Join the discussion on kottke.org</a> →</p>\n\n    ","author":"Jason Kottke","siteTitle":"Kottke","siteHash":"89a883271b4598f9b33ebe87be70d38557bcd266e68aee521a8f93622e0ab723","entryHash":"322c95d019dbf53b785a45a74527cb9435ff7e833fc05b688bbe5c563a94db7b","category":"default"}