{"title":"Los Angeles area meet-up for CWT fans","link":"https://feeds.feedblitz.com/~/904095335/0/marginalrevolution~Los-Angeles-area-meetup-for-CWT-fans.html","date":1725556174000,"content":"<p>Here is <a href=\"https://feeds.feedblitz.com/~/t/0/0/marginalrevolution/~https://conversationswithtyler.com/event/los-angeles-listener-meetup/\" target=\"_blank\">the link</a>, hope to see you there!  October 16, and you do need to pre-register.</p>\r\n<p>The post <a href=\"https://feeds.feedblitz.com/~/t/0/0/marginalrevolution/~https://marginalrevolution.com/marginalrevolution/2024/09/los-angeles-area-meet-up-for-cwt-fans.html\">Los Angeles area meet-up for CWT fans</a> appeared first on <a href=\"https://feeds.feedblitz.com/~/t/0/0/marginalrevolution/~https://marginalrevolution.com\">Marginal REVOLUTION</a>.</p>\r\n<img height=\"1\" width=\"1\" src=\"https://feeds.feedblitz.com/~/i/904095335/0/marginalrevolution\" />\r\n<div><a href=\"https://feeds.feedblitz.com/_/28/904095335/marginalrevolution\"><img height=\"20\" src=\"https://assets.feedblitz.com/i/fblike20.png\" /></a> <a href=\"https://feeds.feedblitz.com/_/29/904095335/marginalrevolution,\"><img height=\"20\" src=\"https://assets.feedblitz.com/i/pinterest20.png\" /></a> <a href=\"https://feeds.feedblitz.com/_/24/904095335/marginalrevolution\"><img height=\"20\" src=\"https://assets.feedblitz.com/i/x.png\" /></a> <a href=\"https://feeds.feedblitz.com/_/19/904095335/marginalrevolution\"><img height=\"20\" src=\"https://assets.feedblitz.com/i/email20.png\" /></a> <a href=\"https://feeds.feedblitz.com/_/20/904095335/marginalrevolution\"><img height=\"20\" src=\"https://assets.feedblitz.com/i/rss20.png\" /></a> <a href=\"https://marginalrevolution.com/marginalrevolution/2024/09/los-angeles-area-meet-up-for-cwt-fans.html#respond\"><img height=\"20\" src=\"https://assets.feedblitz.com/i/comments20.png\" /></a> <a href=\"https://marginalrevolution.com/marginalrevolution/2024/09/los-angeles-area-meet-up-for-cwt-fans.html/feed\"><img height=\"20\" src=\"https://assets.feedblitz.com/i/commentsrss20.png\" /></a> </div>","author":"Tyler Cowen","siteTitle":"Marginal Revolution","siteHash":"242a3a39129b36e0c574c3796ca7ef3cf8af967286c2998fabf7240d1ad52a47","entryHash":"33bb3f9e7aa3847450e0232430a02e63ea47e8110f02d0ec3c8ac7422d2b9260","category":"Sites"}