{"title":"two figs, a double portrait","link":"https://keningzhu.com/journal/two-figs-a-double-portrait","date":1726737720000,"content":" \n\n\n\n\n\n\n\n\n\n\n\n\n\n\n\n\n\n\n\n\n\n\n\n\n\n\n\n\n\n\n\n\n\n\n\n\n\n\n\n\n\n\n  \n\n    \n  \n    \n\n      \n\n      \n        <figure>\n          \n        \n        \n\n        \n          \n            \n          \n            \n                \n                \n                \n                \n                \n                \n                \n                <img src=\"https://images.squarespace-cdn.com/content/v1/51e8148de4b01c1eb79c1977/086dbd63-c3f5-4e5e-8c25-f73ed90f489e/9%3A16+-+figs.jpg?format=1000w\" width=\"3191\" height=\"3200\" srcset=\"https://images.squarespace-cdn.com/content/v1/51e8148de4b01c1eb79c1977/086dbd63-c3f5-4e5e-8c25-f73ed90f489e/9%3A16+-+figs.jpg?format=100w 100w, https://images.squarespace-cdn.com/content/v1/51e8148de4b01c1eb79c1977/086dbd63-c3f5-4e5e-8c25-f73ed90f489e/9%3A16+-+figs.jpg?format=300w 300w, https://images.squarespace-cdn.com/content/v1/51e8148de4b01c1eb79c1977/086dbd63-c3f5-4e5e-8c25-f73ed90f489e/9%3A16+-+figs.jpg?format=500w 500w, https://images.squarespace-cdn.com/content/v1/51e8148de4b01c1eb79c1977/086dbd63-c3f5-4e5e-8c25-f73ed90f489e/9%3A16+-+figs.jpg?format=750w 750w, https://images.squarespace-cdn.com/content/v1/51e8148de4b01c1eb79c1977/086dbd63-c3f5-4e5e-8c25-f73ed90f489e/9%3A16+-+figs.jpg?format=1000w 1000w, https://images.squarespace-cdn.com/content/v1/51e8148de4b01c1eb79c1977/086dbd63-c3f5-4e5e-8c25-f73ed90f489e/9%3A16+-+figs.jpg?format=1500w 1500w, https://images.squarespace-cdn.com/content/v1/51e8148de4b01c1eb79c1977/086dbd63-c3f5-4e5e-8c25-f73ed90f489e/9%3A16+-+figs.jpg?format=2500w 2500w\" loading=\"lazy\" />\n\n            \n          \n        \n          \n        \n\n        \n      \n        </figure>\n      \n\n    \n  \n\n\n  \n\n\n <hr />\n\n\n  <p>it seems that whenever I eat figs for breakfast, I can’t help but paint them. they are just so beautiful - especially when cut in half; the way that the sharpness of the cut form contrasts with the swirling, throbbing universe of seeds (and dead bee matter?) within it. all of that is encased in a velvety purple shell. </p><p>since I painted <a href=\"https://keningzhu.com/journal/end-of-summer-figs-and-plums\" target=\"_blank\">figs in my sketchbook</a>, in gouache, a few weeks ago, I wanted to paint a more illustrative graphic rendition of these figs. something with a bit of a japanese woodblock print vibe? only a few colors. clean and sharp. printable on small postcard, or, idk, an oracle deck inspired by the geometry of mysterious, sensuous fruit. </p>\n\n\n\n\n\n\n\n\n\n\n\n\n\n\n\n\n\n\n\n\n\n  \n  \n\n\n\n<hr /> \n\n\n\n\n\n\n\n\n\n\n\n\n\n\n\n\n\n\n\n\n\n\n\n\n\n\n\n\n\n\n\n\n\n\n\n\n\n\n\n\n\n\n  \n\n    \n  \n    \n\n      \n\n      \n        <figure>\n          \n        \n        \n\n        \n          \n            \n          \n            \n                \n                \n                \n                \n                \n                \n                \n                <img src=\"https://images.squarespace-cdn.com/content/v1/51e8148de4b01c1eb79c1977/3044a061-c420-4d2d-b2d9-669090dfa818/9%3A16+-+figs+photo.jpg?format=1000w\" width=\"4032\" height=\"3024\" srcset=\"https://images.squarespace-cdn.com/content/v1/51e8148de4b01c1eb79c1977/3044a061-c420-4d2d-b2d9-669090dfa818/9%3A16+-+figs+photo.jpg?format=100w 100w, https://images.squarespace-cdn.com/content/v1/51e8148de4b01c1eb79c1977/3044a061-c420-4d2d-b2d9-669090dfa818/9%3A16+-+figs+photo.jpg?format=300w 300w, https://images.squarespace-cdn.com/content/v1/51e8148de4b01c1eb79c1977/3044a061-c420-4d2d-b2d9-669090dfa818/9%3A16+-+figs+photo.jpg?format=500w 500w, https://images.squarespace-cdn.com/content/v1/51e8148de4b01c1eb79c1977/3044a061-c420-4d2d-b2d9-669090dfa818/9%3A16+-+figs+photo.jpg?format=750w 750w, https://images.squarespace-cdn.com/content/v1/51e8148de4b01c1eb79c1977/3044a061-c420-4d2d-b2d9-669090dfa818/9%3A16+-+figs+photo.jpg?format=1000w 1000w, https://images.squarespace-cdn.com/content/v1/51e8148de4b01c1eb79c1977/3044a061-c420-4d2d-b2d9-669090dfa818/9%3A16+-+figs+photo.jpg?format=1500w 1500w, https://images.squarespace-cdn.com/content/v1/51e8148de4b01c1eb79c1977/3044a061-c420-4d2d-b2d9-669090dfa818/9%3A16+-+figs+photo.jpg?format=2500w 2500w\" loading=\"lazy\" />\n\n            \n          \n        \n          \n        \n\n        \n      \n        </figure>\n      \n\n    \n  \n\n\n  \n\n\n <hr />\n\n\n  <p><em>PS. I suddenly remember where the visual inspiration came from. these </em><a href=\"https://publicdomainreview.org/collection/japanese-fireworks-catalogues/\" target=\"_blank\"><em>japanese firework catalogue illustrations</em></a><em>, from the public domain archive. I saw these a few months ago while looking at </em><a href=\"https://keningzhu.com/journal/build-a-labyrinth-not-a-funnel\" target=\"_blank\"><em>labyrinths</em></a><em>, and they must have sprouted something in my mind.</em> </p>\n\n\n\n\n\n\n\n\n\n\n\n\n\n\n\n\n\n\n\n\n\n  \n  \n\n\n\n<hr /> \n\n\n  <p><a href=\"https://keningzhu.com/journal/tag/living+fruit\">more fruit art </a></p>\n\n\n\n\n\n\n\n\n\n\n\n\n\n\n\n\n\n\n\n\n\n  \n  \n\n\n\n ","author":"Kening Zhu","siteTitle":"kening zhu","siteHash":"ef8a94b9fc20c32a4ee7d94ee971337d278e8b2fafe747123e4eb5cea026e84e","entryHash":"37a35f5fbeac7f568b3363a15786189fa84a2be9947e76c9d04efffb8921c641","category":"Sites"}