{"title":"Copy the Shrug Emoji. A website for copying the shrug emoji. Too...","link":"https://kottke.org/24/05/0044541-copy-the-shrug-emoji-a","date":1714679142000,"content":"\n        <p><a href=\"https://copyshrugemoji.com/\">Copy the Shrug Emoji</a>. A website for copying the shrug emoji. Too cute? Ruins it? ¯\\_(ツ)_/¯</p>\n\n        \n\n        \n\n         <p>💬 <a href=\"https://kottke.org/24/05/0044541-copy-the-shrug-emoji-a\">Join the discussion on kottke.org</a> →</p>\n\n    ","author":"Edith Zimmerman","siteTitle":"Kottke","siteHash":"89a883271b4598f9b33ebe87be70d38557bcd266e68aee521a8f93622e0ab723","entryHash":"400134461ec5ac6e592be07b47ac3cbb89d1455243a21f52a0d1fa8f3c47cf49","category":"default"}