{"title":"Best Happy Meal EVER: the Fantastic \"discovery\" Of Artist Wes Cook!","link":"http://bestof.metafilter.com/2024/10/Best-Happy-Meal-EVER-The-fantastic-discovery-of-artist-Wes-Cook","date":1729171924000,"content":"<p>One fine day in 2003, a man stopped in a McDonald's for a meal, <a href=\"https://www.metafilter.com/205908/Look-at-the-thing\">but instead discovered the amazing artist, Wes Cook</a>. Take the 20 minutes and enjoy this magical story that zig zags along on a fantastic journey, you won't be disappointed!</p><p><a href=\"https://www.metafilter.com/205908/Look-at-the-thing\"><img src=\"//mefi.us/images/bestof/3BEDD29C8371E9998EFC2CF4F55A9655.jpg\" width=\"500\" height=\"300\" /></a></p>","author":"Brandon Blatcher","siteTitle":"Best of MetaFilter","siteHash":"da9b129197e360b054d48df4b2b523c9cf9eb040c0f8107f5b90f9a1588086c5","entryHash":"49dc13c2760c9542c0e7bb241eae471deccf949102f2e1d4e2aaf268fb61cbf2","category":"Sites"}