{"title":"","link":"http://scripting.com/2024/07/14.html#a130118","date":1720962078000,"content":"BTW, if Biden steps aside don't expect the Repubs won't sue saying it's illegal, so guess what -- not only don't you get Biden, you don't even get a replacement. The election will be like a Russian election, with just one actual candidate on the ballot and a few total losers for appearances. A great card to hold in your pocket. I bet they have the arguments already written.","author":"","siteTitle":"Scripting News","siteHash":"d6ad59631287cc248e52fdfe0c4f962c0fd08643d455b40f799700d8b2f97c65","entryHash":"58b1eaec6e80ce97bccd6ea7f6c980c00ffb06260e026c1ef54464f0af681a19","category":"default"}