{"title":"How Not to Get Screwed Buying a Used Car","link":"https://kottke.org/24/05/how-not-to-get-screwed-buying-a-used-car-1","date":1716410329000,"content":"\n        <p></p>\n\n<p>This video about how not to get screwed buying a used car crams an astounding amount of good information into three minutes.</p>\n\n<p><strong>Update:</strong> Bold claim by Robin Sloan <a href=\"https://twitter.com/robinsloan/status/732281852245872640\">on Twitter</a>:</p>\n\n<blockquote><p>The calm density of this video is way more “future of visual communication” than 99% of claimants to that title</p></blockquote>\n\n<p>I agree. That video contained more information than a 44-minute episode of Mythbusters but the pace and energy were more relaxed.</p>\n\n         <p><em>[This is a vintage post originally from May 2016.]</em></p>\n\n         <p><strong>Tags:</strong> <a href=\"https://kottke.org/tag/cars\">cars</a> · <a href=\"https://kottke.org/tag/how%20to\">how to</a> · <a href=\"https://kottke.org/tag/Robin%20Sloan\">Robin Sloan</a> · <a href=\"https://kottke.org/tag/timeless%20posts\">timeless posts</a> · <a href=\"https://kottke.org/tag/video\">video</a></p>\n\n        \n\n    ","author":"Jason Kottke","siteTitle":"Kottke","siteHash":"89a883271b4598f9b33ebe87be70d38557bcd266e68aee521a8f93622e0ab723","entryHash":"64f502b0325586e82255137bbf08bc2840e5d1d68c9ec35bf8f4bcf4bcd9b117","category":"default"}