{"title":"Amazing stat about the disappearance of bands from the UK music charts...","link":"https://kottke.org/24/08/0045077-amazing-stat-about-the-di","date":1722980208000,"content":"\n        Amazing stat about <a href=\"https://youtu.be/x8n7Sqfh0Yo?t=1780\">the disappearance of bands from the UK music charts</a> (29:40 mark): in the first half of the 80s, bands were #1 for 146 weeks; the first half of the 90s, it was 141 weeks. In the 20s so far: 3 weeks that songs by bands were #1. 🤯\n\n        \n\n        \n\n         <p>💬 <a href=\"https://kottke.org/24/08/0045077-amazing-stat-about-the-di\">Join the discussion on kottke.org</a> →</p>\n\n    ","author":"Jason Kottke","siteTitle":"Kottke","siteHash":"89a883271b4598f9b33ebe87be70d38557bcd266e68aee521a8f93622e0ab723","entryHash":"68a901cb5ec3be804401d808c5fc4f34c06bdb9519f92597d0f489c4f8ab0dee","category":"default"}