{"title":"","link":"http://scripting.com/2024/12/09.html#a165448","date":1733763288000,"content":"I bet a lot of people who voted for Trump hoped they were voting for <a href=\"https://en.wikipedia.org/wiki/James_Stewart\">Jimmy Stewart</a> in <a href=\"https://en.wikipedia.org/wiki/Mr._Smith_Goes_to_Washington\">Mr Smith goes to Washington</a>, or <a href=\"https://en.wikipedia.org/wiki/It%27s_a_Wonderful_Life\">It's a Wonderful Life</a>. I think they may be surprised to find that they actually voted for <a href=\"https://en.wikipedia.org/wiki/Mr._Potter\">Mr Potter</a> or <a href=\"https://en.wikipedia.org/wiki/Ebenezer_Scrooge\">Ebeneezer Scrooge</a>. Look for a <a href=\"https://christmas.com/what-does-it-mean-to-get-a-lump-of-coal-in-your-christmas-stocking/\">lump of coal</a> in the stocking.","author":"","siteTitle":"Scripting News","siteHash":"d6ad59631287cc248e52fdfe0c4f962c0fd08643d455b40f799700d8b2f97c65","entryHash":"74e231ff4ef42d6f418f23df1b046b96bc08b3b3c4dea32859916d9d1bcd7a85","category":"Sites"}