{"title":"Stay sane even though the news is trying to make us crazy","link":"http://scripting.com/2024/07/15/122832.html?title=staySaneEvenThoughTheNewsIsTryingToMakeUsCrazy","date":1721046512000,"content":"<p>We should hire an intern at some J-school to keep track of all of my tweets, write them down, then translate each into a rule for what a news organization should do instead of not do. Flip the sense of the rule in other words.</p>\n<p>Then we feed those rules to an AI.</p>\n<p>Then we flow in the news stories of the day from various sites through the same AI for translation. Yes I know they'd complain <a href=\"https://www.dictionary.com/browse/vociferous\">vociferously</a>, but which ones you use don't matter because the AI algorithm will translate whatever they are to Dave Winer tense.</p>\n<p>Then of course publish them to another site called The News That Helps Us All Stay Sane. </p>","author":"","siteTitle":"Scripting News","siteHash":"d6ad59631287cc248e52fdfe0c4f962c0fd08643d455b40f799700d8b2f97c65","entryHash":"8594520ac71e0be1b7af56e50ddda96330526a3dcad1b86d49bcdccf50f1e2b7","category":"default"}