{"title":"Old white dudes with sweet hearts","link":"http://scripting.com/2024/08/10/154722.html?title=oldWhiteDudesWithSweetHearts","date":1723304842000,"content":"<p>At first I didn't like White Dudes for Harris but now I get it.</p>\n<p>I saw a guy who'd normally I'd think of as a MAGA, in the crowd behind Kamala yesterday while she spoke, I thought yeah us old white dudes need permission to have sweet hearts. It's time for us to be happy too. Why the f not.</p>\n<p></p><div><img src=\"https://imgs.scripting.com/2024/08/10/oldWhiteMenCanHaveSweetHeartsToo.png\" />This picture is just right. </div><p></p>","author":"","siteTitle":"Scripting News","siteHash":"d6ad59631287cc248e52fdfe0c4f962c0fd08643d455b40f799700d8b2f97c65","entryHash":"956b298139c77dfe8474310ac3da3c7d01e4329e24e89fba49427da43fc69012","category":"default"}