{"title":"Looking to relax or fall asleep? Try Sleep Baseball (aka &#8220;baseball radio...","link":"https://kottke.org/24/05/0044521-looking-to-relax-or-fall","date":1714768504000,"content":"\n        Looking to relax or fall asleep? Try <a href=\"https://www.sleepbaseball.com/\">Sleep Baseball</a> (aka “baseball radio ASMR”). “Northwoods Baseball Sleep Radio is a full-length fake baseball game. There is no yelling, no loud commercials, no weird volume spikes.”\n\n        \n\n        \n\n         <p>💬 <a href=\"https://kottke.org/24/05/0044521-looking-to-relax-or-fall\">Join the discussion on kottke.org</a> →</p>\n\n    ","author":"Jason Kottke","siteTitle":"Kottke","siteHash":"89a883271b4598f9b33ebe87be70d38557bcd266e68aee521a8f93622e0ab723","entryHash":"9db5135fa4edb1b45ee8d7e429a1c44418ae42d8fbbf2fbcb0d74774db19d723","category":"default"}