{"title":"MeFiCoFo","link":"http://bestof.metafilter.com/2024/11/MeFiCoFo","date":1731143837000,"content":"<p><em>As of November 1, 2024 ... the Metafilter Community Foundation exists as an officially registered Delaware nonprofit non-stock corporation.</em>. Yay! In Metatalk, 1adam12 has <a href=\"https://metatalk.metafilter.com/26502/Quick-Nonprofit-Update\">a Quick Nonprofit Update</a> from the Interim Board. (Also of site interest, some thoughts from warriorqueen on <a href=\"https://www.metafilter.com/206212/Seeking-community-in-the-face-of-the-US-election\">Seeking community in the face of the US election</a>.)</p>","author":"taz","siteTitle":"Best of MetaFilter","siteHash":"da9b129197e360b054d48df4b2b523c9cf9eb040c0f8107f5b90f9a1588086c5","entryHash":"9dbf7afddfeae6a987855ba8b4d1cabf582a638ffd79d92f2a64e6648f69547a","category":"Sites"}