{"title":"Modern Pen Pal","link":"http://bestof.metafilter.com/2024/06/Modern-Pen-Pal","date":1719217134000,"content":"<p><em>depending on whim, you may also receive an artifact of some type</em> ... In Metatalk, chiefthe re-ups their <a href=\"https://metatalk.metafilter.com/26457/The-Continuing-Ongoing-Modern-Pen-Pal-Project\">Continuing Ongoing Modern Pen Pal Project</a>, wherein they post a handwritten letter to any mefite requesting one. Sweet! ✍ ✉️</p>","author":"taz","siteTitle":"Best of MetaFilter","siteHash":"da9b129197e360b054d48df4b2b523c9cf9eb040c0f8107f5b90f9a1588086c5","entryHash":"aea23c78d4bf7cd4b4f1cbde9e812732ff8eb4bf8905b636d40206e85a8bf474","category":"default"}