{"title":"Talkin 'bout My (podcast) Generation ...","link":"http://bestof.metafilter.com/2024/09/Talkin-bout-my-podcast-generation","date":1727695910000,"content":"<p><img src=\"//mefi.us/images/bestof/A24FCC4D7DB772F89E0AC2AF98B6BF85.jpg\" width=\"500\" height=\"334\" alt=\"photo of a laptop and a spiral notebook with an image of a cell phone on it that itself has the image of a microphone on it\" /><br /><span>image via pixabay.com</span></p><p>Rhaomi posted about Google's NotebookLM (AI-powered research and writing assistant), and its interesting \"unassuming\" option of turning your uploaded texts, links, docs, audio clips, etc., into source material for an <em>extremely</em> convincing virtual podcast with the surprising \"Audio Overview\" tool. <a href=\"https://www.metafilter.com/205679/Podcast-all-the-things\">Read all about it</a> ... or, in fact, <a href=\"https://notebooklm.google.com/notebook/f9dc5db9-d81a-4465-b0b5-27bb7dc38d4c/audio\">listen to the podcast about us reading all about it</a>. Amazing.</p>","author":"taz","siteTitle":"Best of MetaFilter","siteHash":"da9b129197e360b054d48df4b2b523c9cf9eb040c0f8107f5b90f9a1588086c5","entryHash":"c8b64d13bc7f4595953246ebab65830bc10879ed75b148c67b0c20bcb178c8f1","category":"Sites"}