{"title":"Carpenter&#8217;s Symphony","link":"https://kottke.org/24/10/carpenters-symphony","date":1729632198000,"content":"\n        <p></p>\n\n<p>I love this: a carpenter fires his nail gun in time to the music of a band practicing or performing next door. Music, artistry, and playfulness is everywhere.</p>\n\n        \n\n         <p><strong>Tags:</strong> <a href=\"https://kottke.org/tag/music\">music</a> · <a href=\"https://kottke.org/tag/video\">video</a></p>\n\n         <p>💬 <a href=\"https://kottke.org/24/10/carpenters-symphony\">Join the discussion on kottke.org</a> →</p>\n\n    ","author":"Jason Kottke","siteTitle":"Kottke","siteHash":"89a883271b4598f9b33ebe87be70d38557bcd266e68aee521a8f93622e0ab723","entryHash":"f46afb1265581c1631696fae17199a2a4970ef03551756f113b06552a6aabae4","category":"Sites"}