{"title":"","link":"http://scripting.com/2024/06/08.html#a135657","date":1717855017000,"content":"I wonder if reporters know that Wikipedia hallucinates too?? And since they so often consider Wikipedia authoritative, that means reporters and their publications hallucinate as well.","author":"","siteTitle":"Scripting News","siteHash":"d6ad59631287cc248e52fdfe0c4f962c0fd08643d455b40f799700d8b2f97c65","entryHash":"f8e195bd78846282d38c0ae4062afdca6cd8bd211cd01052789e2acf05cafa9b","category":"default"}